odoo/addons/sale_loyalty_order_suggestion/README.rst
odoo/addons/sale_loyalty_order_suggestion/__init__.py
odoo/addons/sale_loyalty_order_suggestion/__manifest__.py
odoo/addons/sale_loyalty_order_suggestion/i18n/es.po
odoo/addons/sale_loyalty_order_suggestion/i18n/it.po
odoo/addons/sale_loyalty_order_suggestion/i18n/sale_loyalty_order_suggestion.pot
odoo/addons/sale_loyalty_order_suggestion/models/__init__.py
odoo/addons/sale_loyalty_order_suggestion/models/sale_order.py
odoo/addons/sale_loyalty_order_suggestion/readme/CONTRIBUTORS.md
odoo/addons/sale_loyalty_order_suggestion/readme/DESCRIPTION.md
odoo/addons/sale_loyalty_order_suggestion/readme/USAGE.md
odoo/addons/sale_loyalty_order_suggestion/security/ir.model.access.csv
odoo/addons/sale_loyalty_order_suggestion/static/description/icon.png
odoo/addons/sale_loyalty_order_suggestion/static/description/index.html
odoo/addons/sale_loyalty_order_suggestion/static/src/js/suggest_promotion_widget.esm.js
odoo/addons/sale_loyalty_order_suggestion/static/src/xml/suggest_promotion.xml
odoo/addons/sale_loyalty_order_suggestion/tests/__init__.py
odoo/addons/sale_loyalty_order_suggestion/tests/test_sale_loyalty_order_suggestion.py
odoo/addons/sale_loyalty_order_suggestion/views/sale_order_views.xml
odoo/addons/sale_loyalty_order_suggestion/wizard/__init__.py
odoo/addons/sale_loyalty_order_suggestion/wizard/sale_loyalty_reward_wizard.py
odoo/addons/sale_loyalty_order_suggestion/wizard/sale_loyalty_reward_wizard_views.xml
odoo_addon_sale_loyalty_order_suggestion-18.0.1.0.0.4.dist-info/METADATA
odoo_addon_sale_loyalty_order_suggestion-18.0.1.0.0.4.dist-info/WHEEL
odoo_addon_sale_loyalty_order_suggestion-18.0.1.0.0.4.dist-info/top_level.txt
odoo_addon_sale_loyalty_order_suggestion-18.0.1.0.0.4.dist-info/RECORD
